Workbook
Name Grade: 'Grades & Desig'!$D$3:$F$9
Name Payroll: 'Payroll Sheet'!$B$4:$M$24

Sheet Payroll Sheet
B4: E-Code | C4: Name | D4: Grade | E4: Date of Brith | F4: Basic Salary | G4: Conv Allow | H4: House Rent | I4: COLA | J4: Gross Salary | K4: Tax Rate | L4: Tax | M4: Net Salary | O4: Tax Slabs
B5: EN1001 | C5: Khalid Pervez | D5: M1 | E5: 24031 | F5: 75000 | G5: =0.12*F5 -> 9000 | H5: =0.2*F5 -> 15000 | I5: =0.06*F5 -> 4500 | J5: =F5+G5+H5+I5 -> 103500 | K5: =IF(J5>95000,12%,IF(J5>90000,11.5%,IF(J5>85000,11%,IF(J5>80000,10.5%,IF(J5>75000,10%,IF(J5>70000,9.5%,IF(J5>65000,9%,IF(J5>60000,8.5%,IF(J5>55000,8%,IF(J5>50000,7.5%,IF(J5>45000,7%,IF(J5>40000,6.5%,IF(J5>35000,6%,IF(J5>30000,5.5%,IF(J5>25000,5%,IF(J5>20000,4.5%,IF(J5>15000,4%,IF(J5<14999,3.5%,FALSE)))))))))))))))))) -> 0.12 | L5: =K5*J5 -> 12420 | M5: =J5-L5 -> 91080 | O5: Starting | P5: Ending | Q5: Tax Rate
B6: EN1002 | C6: Anwar Abdullah | D6: M2 | E6: 26390 | F6: 56000 | G6: =0.12*F6 -> 6720 | H6: =0.2*F6 -> 11200 | I6: =0.06*F6 -> 3360 | J6: =F6+G6+H6+I6 -> 77280 | K6: =IF(J6>95000,12%,IF(J6>90000,11.5%,IF(J6>85000,11%,IF(J6>80000,10.5%,IF(J6>75000,10%,IF(J6>70000,9.5%,IF(J6>65000,9%,IF(J6>60000,8.5%,IF(J6>55000,8%,IF(J6>50000,7.5%,IF(J6>45000,7%,IF(J6>40000,6.5%,IF(J6>35000,6%,IF(J6>30000,5.5%,IF(J6>25000,5%,IF(J6>20000,4.5%,IF(J6>15000,4%,IF(J6<14999,3.5%,FALSE)))))))))))))))))) -> 0.1 | L6: =K6*J6 -> 7728 | M6: =J6-L6 -> 69552 | O6: 0 | P6: 14999 | Q6: 0.035
B7: EN1003 | C7: Zia Habib | D7: C1 | E7: 29768 | F7: 15660 | G7: =0.12*F7 -> 1879.2 | H7: =0.2*F7 -> 3132 | I7: =0.06*F7 -> 939.6 | J7: =F7+G7+H7+I7 -> 21610.8 | K7: =IF(J7>95000,12%,IF(J7>90000,11.5%,IF(J7>85000,11%,IF(J7>80000,10.5%,IF(J7>75000,10%,IF(J7>70000,9.5%,IF(J7>65000,9%,IF(J7>60000,8.5%,IF(J7>55000,8%,IF(J7>50000,7.5%,IF(J7>45000,7%,IF(J7>40000,6.5%,IF(J7>35000,6%,IF(J7>30000,5.5%,IF(J7>25000,5%,IF(J7>20000,4.5%,IF(J7>15000,4%,IF(J7<14999,3.5%,FALSE)))))))))))))))))) -> 0.045 | L7: =K7*J7 -> 972.486 | M7: =J7-L7 -> 20638.314 | O7: 15000 | P7: 19999 | Q7: 0.04
B8: EN1004 | C8: Nauman Usmani | D8: O2 | E8: 29748 | F8: 27000 | G8: =0.12*F8 -> 3240 | H8: =0.2*F8 -> 5400 | I8: =0.06*F8 -> 1620 | J8: =F8+G8+H8+I8 -> 37260 | K8: =IF(J8>95000,12%,IF(J8>90000,11.5%,IF(J8>85000,11%,IF(J8>80000,10.5%,IF(J8>75000,10%,IF(J8>70000,9.5%,IF(J8>65000,9%,IF(J8>60000,8.5%,IF(J8>55000,8%,IF(J8>50000,7.5%,IF(J8>45000,7%,IF(J8>40000,6.5%,IF(J8>35000,6%,IF(J8>30000,5.5%,IF(J8>25000,5%,IF(J8>20000,4.5%,IF(J8>15000,4%,IF(J8<14999,3.5%,FALSE)))))))))))))))))) -> 0.06 | L8: =K8*J8 -> 2235.6 | M8: =J8-L8 -> 35024.4 | O8: 20000 | P8: 24999 | Q8: 0.045
B9: EN1005 | C9: Faisl Iqbal | D9: O2 | E9: 32325 | F9: 21000 | G9: =0.12*F9 -> 2520 | H9: =0.2*F9 -> 4200 | I9: =0.06*F9 -> 1260 | J9: =F9+G9+H9+I9 -> 28980 | K9: =IF(J9>95000,12%,IF(J9>90000,11.5%,IF(J9>85000,11%,IF(J9>80000,10.5%,IF(J9>75000,10%,IF(J9>70000,9.5%,IF(J9>65000,9%,IF(J9>60000,8.5%,IF(J9>55000,8%,IF(J9>50000,7.5%,IF(J9>45000,7%,IF(J9>40000,6.5%,IF(J9>35000,6%,IF(J9>30000,5.5%,IF(J9>25000,5%,IF(J9>20000,4.5%,IF(J9>15000,4%,IF(J9<14999,3.5%,FALSE)))))))))))))))))) -> 0.05 | L9: =K9*J9 -> 1449 | M9: =J9-L9 -> 27531 | O9: 25000 | P9: 29999 | Q9: 0.05
B10: EN1006 | C10: Imran Akthar | D10: C2 | E10: 32569 | F10: 11000 | G10: =0.12*F10 -> 1320 | H10: =0.2*F10 -> 2200 | I10: =0.06*F10 -> 660 | J10: =F10+G10+H10+I10 -> 15180 | K10: =IF(J10>95000,12%,IF(J10>90000,11.5%,IF(J10>85000,11%,IF(J10>80000,10.5%,IF(J10>75000,10%,IF(J10>70000,9.5%,IF(J10>65000,9%,IF(J10>60000,8.5%,IF(J10>55000,8%,IF(J10>50000,7.5%,IF(J10>45000,7%,IF(J10>40000,6.5%,IF(J10>35000,6%,IF(J10>30000,5.5%,IF(J10>25000,5%,IF(J10>20000,4.5%,IF(J10>15000,4%,IF(J10<14999,3.5%,FALSE)))))))))))))))))) -> 0.04 | L10: =K10*J10 -> 607.2 | M10: =J10-L10 -> 14572.8 | O10: 30000 | P10: 34999 | Q10: 0.055
B11: EN1007 | C11: Javed Akram | D11: O1 | E11: 29342 | F11: 41000 | G11: =0.12*F11 -> 4920 | H11: =0.2*F11 -> 8200 | I11: =0.06*F11 -> 2460 | J11: =F11+G11+H11+I11 -> 56580 | K11: =IF(J11>95000,12%,IF(J11>90000,11.5%,IF(J11>85000,11%,IF(J11>80000,10.5%,IF(J11>75000,10%,IF(J11>70000,9.5%,IF(J11>65000,9%,IF(J11>60000,8.5%,IF(J11>55000,8%,IF(J11>50000,7.5%,IF(J11>45000,7%,IF(J11>40000,6.5%,IF(J11>35000,6%,IF(J11>30000,5.5%,IF(J11>25000,5%,IF(J11>20000,4.5%,IF(J11>15000,4%,IF(J11<14999,3.5%,FALSE)))))))))))))))))) -> 0.08 | L11: =K11*J11 -> 4526.4 | M11: =J11-L11 -> 52053.6 | O11: 35000 | P11: 39999 | Q11: 0.06
B12: EN1008 | C12: Allah Dita | D12: C2 | E12: 32183 | F12: 10000 | G12: =0.12*F12 -> 1200 | H12: =0.2*F12 -> 2000 | I12: =0.06*F12 -> 600 | J12: =F12+G12+H12+I12 -> 13800 | K12: =IF(J12>95000,12%,IF(J12>90000,11.5%,IF(J12>85000,11%,IF(J12>80000,10.5%,IF(J12>75000,10%,IF(J12>70000,9.5%,IF(J12>65000,9%,IF(J12>60000,8.5%,IF(J12>55000,8%,IF(J12>50000,7.5%,IF(J12>45000,7%,IF(J12>40000,6.5%,IF(J12>35000,6%,IF(J12>30000,5.5%,IF(J12>25000,5%,IF(J12>20000,4.5%,IF(J12>15000,4%,IF(J12<14999,3.5%,FALSE)))))))))))))))))) -> 0.035 | L12: =K12*J12 -> 483 | M12: =J12-L12 -> 13317 | O12: 40000 | P12: 44999 | Q12: 0.065
B13: EN1009 | C13: Mobin Chaudhry | D13: C1 | E13: 32082 | F13: 16750 | G13: =0.12*F13 -> 2010 | H13: =0.2*F13 -> 3350 | I13: =0.06*F13 -> 1005 | J13: =F13+G13+H13+I13 -> 23115 | K13: =IF(J13>95000,12%,IF(J13>90000,11.5%,IF(J13>85000,11%,IF(J13>80000,10.5%,IF(J13>75000,10%,IF(J13>70000,9.5%,IF(J13>65000,9%,IF(J13>60000,8.5%,IF(J13>55000,8%,IF(J13>50000,7.5%,IF(J13>45000,7%,IF(J13>40000,6.5%,IF(J13>35000,6%,IF(J13>30000,5.5%,IF(J13>25000,5%,IF(J13>20000,4.5%,IF(J13>15000,4%,IF(J13<14999,3.5%,FALSE)))))))))))))))))) -> 0.045 | L13: =K13*J13 -> 1040.175 | M13: =J13-L13 -> 22074.825 | O13: 45000 | P13: 49999 | Q13: 0.07
B14: EN1010 | C14: Faisal Arshad | D14: O2 | E14: 32692 | F14: 24500 | G14: =0.12*F14 -> 2940 | H14: =0.2*F14 -> 4900 | I14: =0.06*F14 -> 1470 | J14: =F14+G14+H14+I14 -> 33810 | K14: =IF(J14>95000,12%,IF(J14>90000,11.5%,IF(J14>85000,11%,IF(J14>80000,10.5%,IF(J14>75000,10%,IF(J14>70000,9.5%,IF(J14>65000,9%,IF(J14>60000,8.5%,IF(J14>55000,8%,IF(J14>50000,7.5%,IF(J14>45000,7%,IF(J14>40000,6.5%,IF(J14>35000,6%,IF(J14>30000,5.5%,IF(J14>25000,5%,IF(J14>20000,4.5%,IF(J14>15000,4%,IF(J14<14999,3.5%,FALSE)))))))))))))))))) -> 0.055 | L14: =K14*J14 -> 1859.55 | M14: =J14-L14 -> 31950.45 | O14: 50000 | P14: 54999 | Q14: 0.075
B15: EN1011 | C15: Shahid Mahmood | D15: C2 | E15: 32365 | F15: 11745 | G15: =0.12*F15 -> 1409.4 | H15: =0.2*F15 -> 2349 | I15: =0.06*F15 -> 704.7 | J15: =F15+G15+H15+I15 -> 16208.1 | K15: =IF(J15>95000,12%,IF(J15>90000,11.5%,IF(J15>85000,11%,IF(J15>80000,10.5%,IF(J15>75000,10%,IF(J15>70000,9.5%,IF(J15>65000,9%,IF(J15>60000,8.5%,IF(J15>55000,8%,IF(J15>50000,7.5%,IF(J15>45000,7%,IF(J15>40000,6.5%,IF(J15>35000,6%,IF(J15>30000,5.5%,IF(J15>25000,5%,IF(J15>20000,4.5%,IF(J15>15000,4%,IF(J15<14999,3.5%,FALSE)))))))))))))))))) -> 0.04 | L15: =K15*J15 -> 648.324 | M15: =J15-L15 -> 15559.776 | O15: 55000 | P15: 59999 | Q15: 0.08
B16: EN1012 | C16: Raza Khan | D16: C2 | E16: 28225 | F16: 11400 | G16: =0.12*F16 -> 1368 | H16: =0.2*F16 -> 2280 | I16: =0.06*F16 -> 684 | J16: =F16+G16+H16+I16 -> 15732 | K16: =IF(J16>95000,12%,IF(J16>90000,11.5%,IF(J16>85000,11%,IF(J16>80000,10.5%,IF(J16>75000,10%,IF(J16>70000,9.5%,IF(J16>65000,9%,IF(J16>60000,8.5%,IF(J16>55000,8%,IF(J16>50000,7.5%,IF(J16>45000,7%,IF(J16>40000,6.5%,IF(J16>35000,6%,IF(J16>30000,5.5%,IF(J16>25000,5%,IF(J16>20000,4.5%,IF(J16>15000,4%,IF(J16<14999,3.5%,FALSE)))))))))))))))))) -> 0.04 | L16: =K16*J16 -> 629.28 | M16: =J16-L16 -> 15102.72 | O16: 60000 | P16: 64999 | Q16: 0.085
B17: EN1013 | C17: Waleed Hussain | D17: O1 | E17: 26482 | F17: 39750 | G17: =0.12*F17 -> 4770 | H17: =0.2*F17 -> 7950 | I17: =0.06*F17 -> 2385 | J17: =F17+G17+H17+I17 -> 54855 | K17: =IF(J17>95000,12%,IF(J17>90000,11.5%,IF(J17>85000,11%,IF(J17>80000,10.5%,IF(J17>75000,10%,IF(J17>70000,9.5%,IF(J17>65000,9%,IF(J17>60000,8.5%,IF(J17>55000,8%,IF(J17>50000,7.5%,IF(J17>45000,7%,IF(J17>40000,6.5%,IF(J17>35000,6%,IF(J17>30000,5.5%,IF(J17>25000,5%,IF(J17>20000,4.5%,IF(J17>15000,4%,IF(J17<14999,3.5%,FALSE)))))))))))))))))) -> 0.075 | L17: =K17*J17 -> 4114.125 | M17: =J17-L17 -> 50740.875 | O17: 65000 | P17: 69999 | Q17: 0.09
... B22: EN1018 | C22: Mariam Rana | D22: O1 | E22: 30848 | F22: 45000 | G22: =0.12*F22 -> 5400 | H22: =0.2*F22 -> 9000 | I22: =0.06*F22 -> 2700 | J22: =F22+G22+H22+I22 -> 62100 | K22: =IF(J22>95000,12%,IF(J22>90000,11.5%,IF(J22>85000,11%,IF(J22>80000,10.5%,IF(J22>75000,10%,IF(J22>70000,9.5%,IF(J22>65000,9%,IF(J22>60000,8.5%,IF(J22>55000,8%,IF(J22>50000,7.5%,IF(J22>45000,7%,IF(J22>40000,6.5%,IF(J22>35000,6%,IF(J22>30000,5.5%,IF(J22>25000,5%,IF(J22>20000,4.5%,IF(J22>15000,4%,IF(J22<14999,3.5%,FALSE)))))))))))))))))) -> 0.085 | L22: =K22*J22 -> 5278.5 | M22: =J22-L22 -> 56821.5 | O22: 90000 | P22: 94999 | Q22: 0.115
B23: EN1019 | C23: Hina Shaikh | D23: M2 | E23: 28764 | F23: 57000 | G23: =0.12*F23 -> 6840 | H23: =0.2*F23 -> 11400 | I23: =0.06*F23 -> 3420 | J23: =F23+G23+H23+I23 -> 78660 | K23: =IF(J23>95000,12%,IF(J23>90000,11.5%,IF(J23>85000,11%,IF(J23>80000,10.5%,IF(J23>75000,10%,IF(J23>70000,9.5%,IF(J23>65000,9%,IF(J23>60000,8.5%,IF(J23>55000,8%,IF(J23>50000,7.5%,IF(J23>45000,7%,IF(J23>40000,6.5%,IF(J23>35000,6%,IF(J23>30000,5.5%,IF(J23>25000,5%,IF(J23>20000,4.5%,IF(J23>15000,4%,IF(J23<14999,3.5%,FALSE)))))))))))))))))) -> 0.1 | L23: =K23*J23 -> 7866 | M23: =J23-L23 -> 70794 | O23: 95000 | Q23: 0.12
B24: EN1020 | C24: Asif Hussian | D24: C1 | E24: 29018 | F24: 19777 | G24: =0.12*F24 -> 2373.24 | H24: =0.2*F24 -> 3955.4 | I24: =0.06*F24 -> 1186.62 | J24: =F24+G24+H24+I24 -> 27292.26 | K24: =IF(J24>95000,12%,IF(J24>90000,11.5%,IF(J24>85000,11%,IF(J24>80000,10.5%,IF(J24>75000,10%,IF(J24>70000,9.5%,IF(J24>65000,9%,IF(J24>60000,8.5%,IF(J24>55000,8%,IF(J24>50000,7.5%,IF(J24>45000,7%,IF(J24>40000,6.5%,IF(J24>35000,6%,IF(J24>30000,5.5%,IF(J24>25000,5%,IF(J24>20000,4.5%,IF(J24>15000,4%,IF(J24<14999,3.5%,FALSE)))))))))))))))))) -> 0.05 | L24: =K24*J24 -> 1364.613 | M24: =J24-L24 -> 25927.647

Sheet Allownce & Tax Rates
C2: Allownces Calculation
C3: Allownce | D3: % of Basic Salary
C4: Convynce | D4: 0.12
C5: House Rent | D5: 0.2
C6: COLA | D6: 0.06
C11: Tax Slabs
C12: Starting | D12: Ending | E12: Tax Rate
C13: 0 | D13: 14999 | E13: 0.035
C14: 15000 | D14: 19999 | E14: 0.04
C15: 20000 | D15: 24999 | E15: 0.045
C16: 25000 | D16: 29999 | E16: 0.05
C17: 30000 | D17: 34999 | E17: 0.055
C18: 35000 | D18: 39999 | E18: 0.06
C19: 40000 | D19: 44999 | E19: 0.065
C20: 45000 | D20: 49999 | E20: 0.07
C21: 50000 | D21: 54999 | E21: 0.075
C22: 55000 | D22: 59999 | E22: 0.08
C23: 60000 | D23: 64999 | E23: 0.085
C24: 65000 | D24: 69999 | E24: 0.09
... C29: 90000 | D29: 94999 | E29: 0.115
C30: 95000 | E30: 0.12

Sheet Grades & Desig
D3: Grade | E3: Description | F3: Pay Scale
D4: M1 | E4: Sr. Manager | F4: 70000-5000-100000
D5: M2 | E5: Manager | F5: 50000-3000-70000
D6: O1 | E6: Sr. Officer | F6: 30000-1500-50000
D7: O2 | E7: Jr. Officer | F7: 20000-1200-30000
D8: C1 | E8: Sr. Clerk | F8: 10000-800-20000
D9: C2 | E9: Jr. Clerk | F9: 6500-500-12000

Sheet Pay Slip
C2: Enter Employee Code | D2: EN1001
C4: Employee PaySlip | L4: Grade | M4: Job Title | N4: Pay Scale
C5: Name | D5: Grade | E5: Job Title | F5: Age (Years) | G5: Pay Scale | H5: Basic Salary | I5: Gross Salary | J5: Net Salary | L5: M1 | M5: Sr. Manager | N5: 70000-5000-100000
C6: =VLOOKUP(D2,'Payroll Sheet'!B5:C24,2,) -> Khalid Pervez | D6: =VLOOKUP(D2,'Payroll Sheet'!B5:D24,3,) -> M1 | E6: =VLOOKUP(D6,'Grades & Desig'!D4:E9,2,) -> Sr. Manager | G6: =VLOOKUP(D6,'Grades & Desig'!D4:F9,3,FALSE) -> 70000-5000-100000 | H6: =VLOOKUP(D2,'Payroll Sheet'!B5:F24,5,FALSE) -> 75000 | I6: =VLOOKUP(D2,'Payroll Sheet'!B5:J24,9,FALSE) -> 103500 | J6: =VLOOKUP(D2,'Payroll Sheet'!B5:M24,12,FALSE) -> 91080 | L6: M2 | M6: Manager | N6: 50000-3000-70000
L7: O1 | M7: Sr. Officer | N7: 30000-1500-50000
L8: O2 | M8: Jr. Officer | N8: 20000-1200-30000
D9: Deductions | E9: Allowances | L9: C1 | M9: Sr. Clerk | N9: 10000-800-20000
D10: Income Tax | E10: Conv. Allowance | F10: House Rent | G10: COLA | L10: C2 | M10: Jr. Clerk | N10: 6500-500-12000
C14: Inwords
C17: formola: =VLOOKUP(D2,'Payroll Sheet'!B5:D24,3,)
C18: job title farmola: =VLOOKUP(D6,'Grades & Desig'!D4:E9,2,)
C19: Basic formola: =VLOOKUP(D2,'Payroll Sheet'!B5:F24,5,FALSE)
