Workbook

Sheet Sheet1
A1: Employee Attendance Sheet | D1: =TEXT(D2,"ddd") -> Mon | E1: =TEXT(E2,"ddd") -> Tue | F1: =TEXT(F2,"ddd") -> Wed | G1: =TEXT(G2,"ddd") -> Thu | H1: =TEXT(H2,"ddd") -> Fri | I1: =TEXT(I2,"ddd") -> Sat | J1: =TEXT(J2,"ddd") -> Sun | K1: =TEXT(K2,"ddd") -> Mon | ... AH1: =TEXT(AH2,"ddd") -> Wed | AI1: Result
A2: S No | B2: Name of Employee | C2: Designation | D2: 44774 | E2: 44775 | F2: 44776 | G2: 44777 | H2: 44778 | I2: 44779 | J2: 44780 | K2: 44781 | L2: 44782 | M2: 44783 | N2: 44784 | O2: 44785 | P2: 44786 | Q2: 44787 | R2: 44788 | S2: 44789 | T2: 44790 | U2: 44791 | V2: 44792 | W2: 44793 | X2: 44794 | Y2: 44795 | Z2: 44796 | AA2: 44797 | AB2: 44798 | AC2: 44799 | AD2: 44800 | AE2: 44801 | AF2: 44802 | AG2: 44803 | AH2: 44804 | AI2: PRESENTY | AJ2: ABSENTY | AK2: SL | AL2: PL | AM2: P.DAYS
A3: =IF(B3="","",1) -> 1 | B3: Asad | C3: Manager | D3: P | E3: P | F3: P | G3: P | H3: P | I3: P | K3: P | L3: P | M3: P | N3: P | O3: P | P3: P | R3: P | S3: P | T3: P | U3: P | V3: P | W3: P | Y3: P | Z3: P | AA3: P | AB3: P | AC3: P | AD3: P | AF3: P | AG3: P | AH3: P | AI3: =COUNTIF(D3:AH3,"P") -> 27 | AJ3: =COUNTIF(D3:AH3,"A") -> 0 | AK3: =COUNTIF(D3:AH3,"SL") -> 0 | AL3: =COUNTBLANK(D3:AH3) -> 4 | AM3: =AI3+AK3+AL3 -> 31
A4: =IF(B4="","",A3+1) -> 2 | B4: Ebad | C4: Designer | D4: P | E4: P | F4: P | G4: P | H4: P | I4: P | K4: P | L4: P | M4: P | N4: P | O4: P | P4: P | R4: P | S4: P | T4: P | U4: P | V4: P | W4: P | Y4: P | Z4: P | AA4: A | AB4: P | AC4: P | AD4: P | AF4: P | AG4: P | AH4: P | AI4: =COUNTIF(D4:AH4,"P") -> 26 | AJ4: =COUNTIF(D4:AH4,"A") -> 1 | AK4: =COUNTIF(D4:AH4,"SL") -> 0 | AL4: =COUNTBLANK(D4:AH4) -> 4 | AM4: =AI4+AK4+AL4 -> 30
A5: =IF(B5="","",A4+1) -> 3 | B5: Afnan | C5: Developer | D5: P | E5: P | F5: P | G5: P | H5: P | I5: P | K5: P | L5: P | M5: P | N5: P | O5: P | P5: P | R5: P | S5: P | T5: P | U5: P | V5: P | W5: P | Y5: P | Z5: P | AA5: P | AB5: P | AC5: P | AD5: P | AF5: P | AG5: P | AH5: P | AI5: =COUNTIF(D5:AH5,"P") -> 27 | AJ5: =COUNTIF(D5:AH5,"A") -> 0 | AK5: =COUNTIF(D5:AH5,"SL") -> 0 | AL5: =COUNTBLANK(D5:AH5) -> 4 | AM5: =AI5+AK5+AL5 -> 31
A6: =IF(B6="","",A5+1) -> 4 | B6: Fayyaz | C6: Jr. Developer | D6: P | E6: P | F6: P | G6: P | H6: P | I6: P | K6: P | L6: P | M6: P | N6: P | O6: P | P6: P | R6: P | S6: P | T6: P | U6: P | V6: P | W6: P | Y6: P | Z6: P | AA6: P | AB6: P | AC6: P | AD6: P | AF6: P | AG6: P | AH6: P | AI6: =COUNTIF(D6:AH6,"P") -> 27 | AJ6: =COUNTIF(D6:AH6,"A") -> 0 | AK6: =COUNTIF(D6:AH6,"SL") -> 0 | AL6: =COUNTBLANK(D6:AH6) -> 4 | AM6: =AI6+AK6+AL6 -> 31
A7: =IF(B7="","",A6+1) -> 5 | B7: Faisal | C7: Designer | D7: P | E7: P | F7: P | G7: P | H7: P | I7: P | K7: P | L7: P | M7: P | N7: P | O7: P | P7: P | R7: P | S7: P | T7: P | U7: P | V7: P | W7: P | Y7: P | Z7: P | AA7: P | AB7: P | AC7: P | AD7: P | AF7: P | AG7: P | AH7: P | AI7: =COUNTIF(D7:AH7,"P") -> 27 | AJ7: =COUNTIF(D7:AH7,"A") -> 0 | AK7: =COUNTIF(D7:AH7,"SL") -> 0 | AL7: =COUNTBLANK(D7:AH7) -> 4 | AM7: =AI7+AK7+AL7 -> 31
A8: =IF(B8="","",A7+1) -> 6 | B8: Naeem | C8: Developer | D8: P | E8: P | F8: P | G8: P | H8: P | I8: P | K8: P | L8: P | M8: P | N8: A | O8: P | P8: P | R8: P | S8: P | T8: P | U8: P | V8: P | W8: A | Y8: P | Z8: P | AA8: P | AB8: P | AC8: P | AD8: P | AF8: P | AG8: P | AH8: P | AI8: =COUNTIF(D8:AH8,"P") -> 25 | AJ8: =COUNTIF(D8:AH8,"A") -> 2 | AK8: =COUNTIF(D8:AH8,"SL") -> 0 | AL8: =COUNTBLANK(D8:AH8) -> 4 | AM8: =AI8+AK8+AL8 -> 29
A9: =IF(B9="","",A8+1) -> 7 | B9: Qasim | C9: Manager | D9: P | E9: P | F9: P | G9: P | H9: P | I9: P | K9: P | L9: P | M9: P | N9: P | O9: P | P9: P | R9: P | S9: P | T9: P | U9: P | V9: P | W9: P | Y9: P | Z9: P | AA9: P | AB9: P | AC9: P | AD9: P | AF9: P | AG9: P | AH9: P | AI9: =COUNTIF(D9:AH9,"P") -> 27 | AJ9: =COUNTIF(D9:AH9,"A") -> 0 | AK9: =COUNTIF(D9:AH9,"SL") -> 0 | AL9: =COUNTBLANK(D9:AH9) -> 4 | AM9: =AI9+AK9+AL9 -> 31
A10: =IF(B10="","",A9+1) -> 8 | B10: Majid | C10: Developer | D10: P | E10: P | F10: P | G10: P | H10: P | I10: P | K10: P | L10: P | M10: P | N10: P | O10: P | P10: P | R10: P | S10: P | T10: P | U10: P | V10: P | W10: P | Y10: P | Z10: P | AA10: P | AB10: P | AC10: P | AD10: P | AF10: P | AG10: P | AH10: P | AI10: =COUNTIF(D10:AH10,"P") -> 27 | AJ10: =COUNTIF(D10:AH10,"A") -> 0 | AK10: =COUNTIF(D10:AH10,"SL") -> 0 | AL10: =COUNTBLANK(D10:AH10) -> 4 | AM10: =AI10+AK10+AL10 -> 31
A11: =IF(B11="","",A10+1) -> 9 | B11: Furqan | C11: Designer | D11: P | E11: P | F11: P | G11: P | H11: P | I11: P | K11: P | L11: P | M11: P | N11: P | O11: P | P11: P | R11: P | S11: P | T11: P | U11: P | V11: P | W11: P | Y11: P | Z11: P | AA11: P | AB11: P | AC11: P | AD11: P | AF11: P | AG11: P | AH11: P | AI11: =COUNTIF(D11:AH11,"P") -> 27 | AJ11: =COUNTIF(D11:AH11,"A") -> 0 | AK11: =COUNTIF(D11:AH11,"SL") -> 0 | AL11: =COUNTBLANK(D11:AH11) -> 4 | AM11: =AI11+AK11+AL11 -> 31
A12: 10 | B12: Farooq | C12: Jr. Developer | D12: P | E12: P | F12: P | G12: P | H12: P | I12: P | K12: P | L12: P | M12: P | N12: P | O12: P | P12: P | R12: P | S12: P | T12: P | U12: P | V12: P | W12: P | Y12: P | Z12: P | AA12: P | AB12: P | AC12: P | AD12: P | AF12: P | AG12: P | AH12: P | AI12: =COUNTIF(D12:AH12,"P") -> 27 | AJ12: =COUNTIF(D12:AH12,"A") -> 0 | AK12: =COUNTIF(D12:AH12,"SL") -> 0 | AL12: =COUNTBLANK(D12:AH12) -> 4 | AM12: =AI12+AK12+AL12 -> 31

Sheet Sheet2
A3: Emp ID | B3: Emp Name | C3: Designation | D3: Basic Salary | E3: Working Days | F3: Overtime | G3: Overtime Amount | H3: PAYMENTS | L3: DEDUCTIONS | P3: NET SALARY
H4: Allowance % | K4: GROSS SALARY | L4: INCOME TAX | M4: PF | N4: Advance Salary | O4: Total Deduction
H5: House Rent | I5: Conveyance | J5: Medical
A6: NO-10001 | B6: Asad | C6: Manager | D6: 60000 | E6: =Sheet1!AM3 -> 31 | F6: 14 | G6: =(D6/30/8)*F6 -> 3500 | H6: =IF(D6>=40000,D6*2.5%,D6*2%) -> 1500 | I6: =IF(D6>=40000,D6*6%,D6*5%) -> 3600 | J6: =IF(D6>=40000,D6*3.5%,D6*3%) -> 2100 | K6: =SUM(H6:J6)+D6/31*E6 -> 67200 | L6: =IF(K6>=50000,K6*1.2%,0) -> 806.4 | M6: =K6*1% -> 672 | N6: =SUMIF(Sheet3!$A$6:$A$15,Sheet2!A6,Sheet3!$AI$6:$AI$15) -> 0
A7: NO-10002 | B7: Ebad | C7: Designer | D7: 25000 | E7: =Sheet1!AM4 -> 30 | F7: 12 | G7: =(D7/30/8)*F7 -> 1250 | H7: =IF(D7>=40000,D7*2.5%,D7*2%) -> 500 | I7: =IF(D7>=40000,D7*6%,D7*5%) -> 1250 | J7: =IF(D7>=40000,D7*3.5%,D7*3%) -> 750 | K7: =SUM(H7:J7)+D7/31*E7 -> 26693.548 | L7: =IF(K7>=50000,K7*1.2%,0) -> 0 | M7: =K7*1% -> 266.93548 | N7: =SUMIF(Sheet3!$A$6:$A$15,Sheet2!A7,Sheet3!$AI$6:$AI$15) -> 0
A8: NO-10003 | B8: Afnan | C8: Developer | D8: 35000 | E8: =Sheet1!AM5 -> 31 | F8: 24 | G8: =(D8/30/8)*F8 -> 3500 | H8: =IF(D8>=40000,D8*2.5%,D8*2%) -> 700 | I8: =IF(D8>=40000,D8*6%,D8*5%) -> 1750 | J8: =IF(D8>=40000,D8*3.5%,D8*3%) -> 1050 | K8: =SUM(H8:J8)+D8/31*E8 -> 38500 | L8: =IF(K8>=50000,K8*1.2%,0) -> 0 | M8: =K8*1% -> 385 | N8: =SUMIF(Sheet3!$A$6:$A$15,Sheet2!A8,Sheet3!$AI$6:$AI$15) -> 0
A9: NO-10004 | B9: Fayyaz | C9: Jr. Developer | D9: 25000 | E9: =Sheet1!AM6 -> 31 | F9: 35 | G9: =(D9/30/8)*F9 -> 3645.8333 | H9: =IF(D9>=40000,D9*2.5%,D9*2%) -> 500 | I9: =IF(D9>=40000,D9*6%,D9*5%) -> 1250 | J9: =IF(D9>=40000,D9*3.5%,D9*3%) -> 750 | K9: =SUM(H9:J9)+D9/31*E9 -> 27500 | L9: =IF(K9>=50000,K9*1.2%,0) -> 0 | M9: =K9*1% -> 275 | N9: =SUMIF(Sheet3!$A$6:$A$15,Sheet2!A9,Sheet3!$AI$6:$AI$15) -> 0
A10: NO-10005 | B10: Faisal | C10: Designer | D10: 35000 | E10: =Sheet1!AM7 -> 31 | F10: 12 | G10: =(D10/30/8)*F10 -> 1750 | H10: =IF(D10>=40000,D10*2.5%,D10*2%) -> 700 | I10: =IF(D10>=40000,D10*6%,D10*5%) -> 1750 | J10: =IF(D10>=40000,D10*3.5%,D10*3%) -> 1050 | K10: =SUM(H10:J10)+D10/31*E10 -> 38500 | L10: =IF(K10>=50000,K10*1.2%,0) -> 0 | M10: =K10*1% -> 385 | N10: =SUMIF(Sheet3!$A$6:$A$15,Sheet2!A10,Sheet3!$AI$6:$AI$15) -> 0
A11: NO-10006 | B11: Naeem | C11: Developer | D11: 40000 | E11: =Sheet1!AM8 -> 29 | F11: 34 | G11: =(D11/30/8)*F11 -> 5666.6667 | H11: =IF(D11>=40000,D11*2.5%,D11*2%) -> 1000 | I11: =IF(D11>=40000,D11*6%,D11*5%) -> 2400 | J11: =IF(D11>=40000,D11*3.5%,D11*3%) -> 1400 | K11: =SUM(H11:J11)+D11/31*E11 -> 42219.355 | L11: =IF(K11>=50000,K11*1.2%,0) -> 0 | M11: =K11*1% -> 422.19355 | N11: =SUMIF(Sheet3!$A$6:$A$15,Sheet2!A11,Sheet3!$AI$6:$AI$15) -> 0
A12: NO-10007 | B12: Qasim | C12: Manager | D12: 65000 | E12: =Sheet1!AM9 -> 31 | F12: 7 | G12: =(D12/30/8)*F12 -> 1895.8333 | H12: =IF(D12>=40000,D12*2.5%,D12*2%) -> 1625 | I12: =IF(D12>=40000,D12*6%,D12*5%) -> 3900 | J12: =IF(D12>=40000,D12*3.5%,D12*3%) -> 2275 | K12: =SUM(H12:J12)+D12/31*E12 -> 72800 | L12: =IF(K12>=50000,K12*1.2%,0) -> 873.6 | M12: =K12*1% -> 728 | N12: =SUMIF(Sheet3!$A$6:$A$15,Sheet2!A12,Sheet3!$AI$6:$AI$15) -> 0
A13: NO-10008 | B13: Majid | C13: Developer | D13: 40000 | E13: =Sheet1!AM10 -> 31 | F13: 45 | G13: =(D13/30/8)*F13 -> 7500 | H13: =IF(D13>=40000,D13*2.5%,D13*2%) -> 1000 | I13: =IF(D13>=40000,D13*6%,D13*5%) -> 2400 | J13: =IF(D13>=40000,D13*3.5%,D13*3%) -> 1400 | K13: =SUM(H13:J13)+D13/31*E13 -> 44800 | L13: =IF(K13>=50000,K13*1.2%,0) -> 0 | M13: =K13*1% -> 448 | N13: =SUMIF(Sheet3!$A$6:$A$15,Sheet2!A13,Sheet3!$AI$6:$AI$15) -> 0
A14: NO-10009 | B14: Furqan | C14: Designer | D14: 55000 | E14: =Sheet1!AM11 -> 31 | F14: 34 | G14: =(D14/30/8)*F14 -> 7791.6667 | H14: =IF(D14>=40000,D14*2.5%,D14*2%) -> 1375 | I14: =IF(D14>=40000,D14*6%,D14*5%) -> 3300 | J14: =IF(D14>=40000,D14*3.5%,D14*3%) -> 1925 | K14: =SUM(H14:J14)+D14/31*E14 -> 61600 | L14: =IF(K14>=50000,K14*1.2%,0) -> 739.2 | M14: =K14*1% -> 616 | N14: =SUMIF(Sheet3!$A$6:$A$15,Sheet2!A14,Sheet3!$AI$6:$AI$15) -> 0
A15: NO-10010 | B15: Farooq | C15: Jr. Developer | D15: 20000 | E15: =Sheet1!AM12 -> 31 | F15: 32 | G15: =(D15/30/8)*F15 -> 2666.6667 | H15: =IF(D15>=40000,D15*2.5%,D15*2%) -> 400 | I15: =IF(D15>=40000,D15*6%,D15*5%) -> 1000 | J15: =IF(D15>=40000,D15*3.5%,D15*3%) -> 600 | K15: =SUM(H15:J15)+D15/31*E15 -> 22000 | L15: =IF(K15>=50000,K15*1.2%,0) -> 0 | M15: =K15*1% -> 220 | N15: =SUMIF(Sheet3!$A$6:$A$15,Sheet2!A15,Sheet3!$AI$6:$AI$15) -> 0

Sheet Sheet3
A3: Emp ID | B3: Emp Name | C3: Designation | D3: Employee Advance Salary Record | AI3: Total Amount
D5: 44774 | E5: 44775 | F5: 44776 | G5: 44777 | H5: 44778 | I5: 44779 | J5: 44780 | K5: 44781 | L5: 44782 | M5: 44783 | N5: 44784 | O5: 44785 | P5: 44786 | Q5: 44787 | R5: 44788 | S5: 44789 | T5: 44790 | U5: 44791 | V5: 44792 | W5: 44793 | X5: 44794 | Y5: 44795 | Z5: 44796 | AA5: 44797 | AB5: 44798 | AC5: 44799 | AD5: 44800 | AE5: 44801 | AF5: 44802 | AG5: 44803 | AH5: 44804
A6: NO-10001 | B6: =VLOOKUP(A6,Sheet2!$A$6:$C$15,2,0) -> Asad | C6: =VLOOKUP(A6,Sheet2!$A$6:$C$15,3,0) -> Manager | AI6: =SUM(D6:AH6) -> 0
A7: NO-10002 | B7: =VLOOKUP(A7,Sheet2!$A$6:$C$15,2,0) -> Ebad | C7: =VLOOKUP(A7,Sheet2!$A$6:$C$15,3,0) -> Designer | AI7: =SUM(D7:AH7) -> 0
A8: NO-10003 | B8: =VLOOKUP(A8,Sheet2!$A$6:$C$15,2,0) -> Afnan | C8: =VLOOKUP(A8,Sheet2!$A$6:$C$15,3,0) -> Developer | AI8: =SUM(D8:AH8) -> 0
A9: NO-10004 | B9: =VLOOKUP(A9,Sheet2!$A$6:$C$15,2,0) -> Fayyaz | C9: =VLOOKUP(A9,Sheet2!$A$6:$C$15,3,0) -> Jr. Developer | AI9: =SUM(D9:AH9) -> 0
A10: NO-10005 | B10: =VLOOKUP(A10,Sheet2!$A$6:$C$15,2,0) -> Faisal | C10: =VLOOKUP(A10,Sheet2!$A$6:$C$15,3,0) -> Designer | AI10: =SUM(D10:AH10) -> 0
A11: NO-10006 | B11: =VLOOKUP(A11,Sheet2!$A$6:$C$15,2,0) -> Naeem | C11: =VLOOKUP(A11,Sheet2!$A$6:$C$15,3,0) -> Developer | AI11: =SUM(D11:AH11) -> 0
A12: NO-10007 | B12: =VLOOKUP(A12,Sheet2!$A$6:$C$15,2,0) -> Qasim | C12: =VLOOKUP(A12,Sheet2!$A$6:$C$15,3,0) -> Manager | AI12: =SUM(D12:AH12) -> 0
A13: NO-10008 | B13: =VLOOKUP(A13,Sheet2!$A$6:$C$15,2,0) -> Majid | C13: =VLOOKUP(A13,Sheet2!$A$6:$C$15,3,0) -> Developer | AI13: =SUM(D13:AH13) -> 0
A14: NO-10009 | B14: =VLOOKUP(A14,Sheet2!$A$6:$C$15,2,0) -> Furqan | C14: =VLOOKUP(A14,Sheet2!$A$6:$C$15,3,0) -> Designer | AI14: =SUM(D14:AH14) -> 0
A15: NO-10010 | B15: =VLOOKUP(A15,Sheet2!$A$6:$C$15,2,0) -> Farooq | C15: =VLOOKUP(A15,Sheet2!$A$6:$C$15,3,0) -> Jr. Developer | AI15: =SUM(D15:AH15) -> 0
